{
  "anim_reacttocliff_faceplantroll_armup_02": [
    {
      "durationTime_ms": 171,
      "triggerTime_ms": 1109,
      "Name": "LiftHeightKeyFrame",
      "heightVariability_mm": 0,
      "height_mm": 87.97908748592343
    },
    {
      "durationTime_ms": 139,
      "triggerTime_ms": 1280,
      "Name": "LiftHeightKeyFrame",
      "heightVariability_mm": 0,
      "height_mm": 91.53776124146607
    },
    {
      "durationTime_ms": 132,
      "triggerTime_ms": 1419,
      "Name": "LiftHeightKeyFrame",
      "heightVariability_mm": 0,
      "height_mm": 0.0
    },
    {
      "durationTime_ms": 198,
      "triggerTime_ms": 2805,
      "Name": "LiftHeightKeyFrame",
      "heightVariability_mm": 0,
      "height_mm": 92.0
    },
    {
      "angleVariability_deg": 0,
      "angle_deg": 1.2149952650070188,
      "triggerTime_ms": 0,
      "Name": "HeadAngleKeyFrame",
      "durationTime_ms": 132
    },
    {
      "angleVariability_deg": 0,
      "angle_deg": 12.845946311950682,
      "triggerTime_ms": 132,
      "Name": "HeadAngleKeyFrame",
      "durationTime_ms": 103
    },
    {
      "angleVariability_deg": 0,
      "angle_deg": -19.999999999999996,
      "triggerTime_ms": 235,
      "Name": "HeadAngleKeyFrame",
      "durationTime_ms": 132
    },
    {
      "angleVariability_deg": 0,
      "angle_deg": -2.590449571609497,
      "triggerTime_ms": 627,
      "Name": "HeadAngleKeyFrame",
      "durationTime_ms": 363
    },
    {
      "angleVariability_deg": 0,
      "angle_deg": 15.684399604797362,
      "triggerTime_ms": 990,
      "Name": "HeadAngleKeyFrame",
      "durationTime_ms": 264
    },
    {
      "angleVariability_deg": 0,
      "angle_deg": -9.87888431549072,
      "triggerTime_ms": 1254,
      "Name": "HeadAngleKeyFrame",
      "durationTime_ms": 132
    },
    {
      "angleVariability_deg": 0,
      "angle_deg": 24.380764007568356,
      "triggerTime_ms": 1386,
      "Name": "HeadAngleKeyFrame",
      "durationTime_ms": 99
    },
    {
      "angleVariability_deg": 0,
      "angle_deg": 26.646272659301754,
      "triggerTime_ms": 1485,
      "Name": "HeadAngleKeyFrame",
      "durationTime_ms": 231
    },
    {
      "angleVariability_deg": 0,
      "angle_deg": -6.8602585792541495,
      "triggerTime_ms": 1716,
      "Name": "HeadAngleKeyFrame",
      "durationTime_ms": 66
    },
    {
      "angleVariability_deg": 0,
      "angle_deg": 10.389990806579588,
      "triggerTime_ms": 1782,
      "Name": "HeadAngleKeyFrame",
      "durationTime_ms": 132
    },
    {
      "angleVariability_deg": 0,
      "angle_deg": -4.232958793640137,
      "triggerTime_ms": 1914,
      "Name": "HeadAngleKeyFrame",
      "durationTime_ms": 99
    },
    {
      "angleVariability_deg": 0,
      "angle_deg": 6.987004756927489,
      "triggerTime_ms": 2013,
      "Name": "HeadAngleKeyFrame",
      "durationTime_ms": 132
    },
    {
      "angleVariability_deg": 0,
      "angle_deg": -2.9659934043884277,
      "triggerTime_ms": 2145,
      "Name": "HeadAngleKeyFrame",
      "durationTime_ms": 66
    },
    {
      "angleVariability_deg": 0,
      "angle_deg": 3.0058054924011226,
      "triggerTime_ms": 2211,
      "Name": "HeadAngleKeyFrame",
      "durationTime_ms": 99
    },
    {
      "angleVariability_deg": 0,
      "angle_deg": 1.5029027462005613,
      "triggerTime_ms": 2310,
      "Name": "HeadAngleKeyFrame",
      "durationTime_ms": 99
    },
    {
      "angleVariability_deg": 0,
      "angle_deg": 0.0,
      "triggerTime_ms": 2409,
      "Name": "HeadAngleKeyFrame",
      "durationTime_ms": 198
    },
    {
      "durationTime_ms": 0,
      "faceCenterY": 0.0,
      "faceCenterX": 0.0,
      "Name": "ProceduralFaceKeyFrame",
      "faceScaleY": 1.0,
      "faceScaleX": 1.0,
      "rightEye": [
        -10.206374107265454,
        0.0,
        1.2220369777691873,
        0.9052803931751328,
        0.0,
        0.5,
        0.5,
        0.5,
        0.5,
        0.5,
        0.5,
        0.5,
        0.5,
        0.0,
        0.0,
        0.0,
        0.0,
        0.0,
        0.0
      ],
      "triggerTime_ms": 0,
      "faceAngle": 0.0,
      "leftEye": [
        9.169666010979592,
        0.0,
        1.214332921016245,
        0.9052803931751328,
        0.0,
        0.5,
        0.5,
        0.5,
        0.5,
        0.5,
        0.5,
        0.5,
        0.5,
        0.0,
        0.0,
        0.0,
        0.0,
        0.0,
        0.0
      ]
    },
    {
      "durationTime_ms": 0,
      "faceCenterY": 0.0,
      "faceCenterX": 0.0,
      "Name": "ProceduralFaceKeyFrame",
      "faceScaleY": 1.0,
      "faceScaleX": 1.0,
      "rightEye": [
        -10.206374107265454,
        0.0,
        1.2220369777691873,
        0.9052803931751328,
        0.0,
        0.5,
        0.5,
        0.5,
        0.5,
        0.5,
        0.5,
        0.5,
        0.5,
        0.0,
        0.0,
        0.0,
        0.0,
        0.0,
        0.0
      ],
      "triggerTime_ms": 165,
      "faceAngle": 0.0,
      "leftEye": [
        9.169666010979592,
        0.0,
        1.214332921016245,
        0.9052803931751328,
        0.0,
        0.5,
        0.5,
        0.5,
        0.5,
        0.5,
        0.5,
        0.5,
        0.5,
        0.0,
        0.0,
        0.0,
        0.0,
        0.0,
        0.0
      ]
    },
    {
      "durationTime_ms": 0,
      "faceCenterY": 0.0,
      "faceCenterX": 0.0,
      "Name": "ProceduralFaceKeyFrame",
      "faceScaleY": 1.0,
      "faceScaleX": 1.0,
      "rightEye": [
        -10.206374107265454,
        0.0,
        1.2220369777691873,
        0.9052803931751328,
        0.0,
        0.5,
        0.5,
        0.5,
        0.5,
        0.5,
        0.5,
        0.5,
        0.5,
        0.0,
        0.0,
        0.0,
        0.0,
        0.0,
        0.0
      ],
      "triggerTime_ms": 367,
      "faceAngle": 0.0,
      "leftEye": [
        9.169666010979592,
        0.0,
        1.214332921016245,
        0.9052803931751328,
        0.0,
        0.5,
        0.5,
        0.5,
        0.5,
        0.5,
        0.5,
        0.5,
        0.5,
        0.0,
        0.0,
        0.0,
        0.0,
        0.0,
        0.0
      ]
    },
    {
      "durationTime_ms": 0,
      "faceCenterY": 0.0,
      "faceCenterX": 0.0,
      "Name": "ProceduralFaceKeyFrame",
      "faceScaleY": 1.0,
      "faceScaleX": 1.0,
      "rightEye": [
        -10.206374107265454,
        0.0,
        1.2220369777691873,
        0.9052803931751328,
        0.0,
        0.5,
        0.5,
        0.5,
        0.5,
        0.5,
        0.5,
        0.5,
        0.5,
        0.0,
        0.0,
        0.0,
        0.0,
        0.0,
        0.0
      ],
      "triggerTime_ms": 627,
      "faceAngle": 0.0,
      "leftEye": [
        9.169666010979592,
        0.0,
        1.214332921016245,
        0.9052803931751328,
        0.0,
        0.5,
        0.5,
        0.5,
        0.5,
        0.5,
        0.5,
        0.5,
        0.5,
        0.0,
        0.0,
        0.0,
        0.0,
        0.0,
        0.0
      ]
    },
    {
      "durationTime_ms": 0,
      "faceCenterY": 1.841156466836438,
      "faceCenterX": 0.0,
      "Name": "ProceduralFaceKeyFrame",
      "faceScaleY": 1.0,
      "faceScaleX": 1.0,
      "rightEye": [
        -10.206374107265454,
        0.0,
        1.2220369777691873,
        0.9052803931751328,
        0.0,
        0.5,
        0.5,
        0.5448564731892063,
        0.5448564731892063,
        0.5448564731892063,
        0.5448564731892063,
        0.5,
        0.5,
        0.05116208855425963,
        0.0,
        0.0,
        0.1966971236388182,
        0.0,
        0.0
      ],
      "triggerTime_ms": 990,
      "faceAngle": 0.0,
      "leftEye": [
        9.169666010979592,
        0.0,
        1.214332921016245,
        0.9052803931751328,
        0.0,
        0.5,
        0.5,
        0.5448564731892063,
        0.5448564731892063,
        0.5448564731892063,
        0.5448564731892063,
        0.5,
        0.5,
        0.05128806549496934,
        0.0,
        0.0,
        0.202566960865721,
        0.0,
        0.0
      ]
    },
    {
      "durationTime_ms": 0,
      "faceCenterY": 4.415130517984381,
      "faceCenterX": 0.0,
      "Name": "ProceduralFaceKeyFrame",
      "faceScaleY": 1.0,
      "faceScaleX": 1.0,
      "rightEye": [
        -10.206374107265454,
        0.0,
        1.2220369777691873,
        0.9052803931751328,
        0.0,
        0.5,
        0.5,
        0.6075667721771865,
        0.6075667721771865,
        0.6075667721771865,
        0.6075667721771865,
        0.5,
        0.5,
        0.1380992882639599,
        0.0,
        0.0,
        0.47168365941750523,
        0.0,
        0.0
      ],
      "triggerTime_ms": 1155,
      "faceAngle": 0.0,
      "leftEye": [
        9.169666010979592,
        0.0,
        1.214332921016245,
        0.9052803931751328,
        0.0,
        0.5,
        0.5,
        0.6075667721771865,
        0.6075667721771865,
        0.6075667721771865,
        0.6075667721771865,
        0.5,
        0.5,
        0.13810033543379863,
        0.0,
        0.0,
        0.485759647170405,
        0.0,
        0.0
      ]
    },
    {
      "durationTime_ms": 0,
      "faceCenterY": 4.1378665007562185,
      "faceCenterX": 0.0,
      "Name": "ProceduralFaceKeyFrame",
      "faceScaleY": 1.0009170770645142,
      "faceScaleX": 0.9962599277148573,
      "rightEye": [
        -10.206374107265454,
        -0.05226138291633396,
        1.225326762400463,
        0.9052803931751328,
        0.0,
        0.4989215803662772,
        0.4989215803662772,
        0.6048216772801034,
        0.6048216772801034,
        0.6014220667958448,
        0.6014220667958448,
        0.4989215803662772,
        0.4989215803662772,
        0.15762060935827393,
        0.0,
        0.0,
        0.4478000794100577,
        0.0,
        0.0
      ],
      "triggerTime_ms": 1386,
      "faceAngle": 0.0,
      "leftEye": [
        9.169666010979592,
        -0.04792633215952129,
        1.2164022615839452,
        0.9052803931751328,
        0.0,
        0.4989047351300366,
        0.4989047351300366,
        0.6053306335097055,
        0.6053306335097055,
        0.6029994416906028,
        0.6029994416906028,
        0.4989047351300366,
        0.4989047351300366,
        0.15724031659654336,
        0.0,
        0.0,
        0.46835426907516764,
        0.0,
        0.0
      ]
    },
    {
      "durationTime_ms": 0,
      "faceCenterY": 0.0,
      "faceCenterX": 0.0,
      "Name": "ProceduralFaceKeyFrame",
      "faceScaleY": 1.6275416612625122,
      "faceScaleX": 0.8442620626719509,
      "rightEye": [
        -10.206374107265454,
        0.0,
        1.578522208770766,
        0.9052803931751328,
        0.0,
        0.39954288891744566,
        0.39954288891744566,
        0.39954288891744566,
        0.39954288891744566,
        0.39954288891744566,
        0.39954288891744566,
        0.39954288891744566,
        0.39954288891744566,
        0.0,
        0.0,
        0.0,
        0.0,
        0.0,
        0.0
      ],
      "triggerTime_ms": 1518,
      "faceAngle": 0.0,
      "leftEye": [
        9.169666010979592,
        0.0,
        1.2882419568399386,
        0.9052803931751328,
        0.0,
        0.2953651062418813,
        0.2953651062418813,
        0.2953651062418813,
        0.2953651062418813,
        0.5,
        0.5,
        0.5,
        0.5,
        0.0,
        0.0,
        0.0,
        0.0,
        0.0,
        0.0
      ]
    },
    {
      "durationTime_ms": 0,
      "faceCenterY": 0.0,
      "faceCenterX": 0.0,
      "Name": "ProceduralFaceKeyFrame",
      "faceScaleY": 1.2008438110351562,
      "faceScaleX": 0.8442620626719509,
      "rightEye": [
        -12.51011094988588,
        0.8983536925807699,
        1.1905229857211055,
        0.8270245005364814,
        0.0,
        0.2953651062418813,
        0.2953651062418813,
        0.2953651062418813,
        0.2953651062418813,
        0.5,
        0.5,
        0.5,
        0.5,
        0.0,
        0.0,
        0.0,
        0.0,
        0.0,
        0.0
      ],
      "triggerTime_ms": 1683,
      "faceAngle": 0.0,
      "leftEye": [
        9.169666010979592,
        0.0,
        1.2882419568399386,
        0.9052803931751328,
        0.0,
        0.5,
        0.5,
        0.5,
        0.5,
        0.5,
        0.5,
        0.5,
        0.5,
        0.0,
        0.0,
        0.0,
        0.0,
        0.0,
        0.0
      ]
    },
    {
      "durationTime_ms": 0,
      "faceCenterY": 0.0,
      "faceCenterX": 0.0,
      "Name": "ProceduralFaceKeyFrame",
      "faceScaleY": 1.586578607559204,
      "faceScaleX": 0.8442620626719509,
      "rightEye": [
        -11.786406337103992,
        0.6161416120765609,
        1.3086933336266617,
        0.8516081247062175,
        0.0,
        0.11464458578679071,
        0.11464458578679071,
        0.11464458578679071,
        0.11464458578679071,
        0.25499474646585274,
        0.25499474646585274,
        0.25499474646585274,
        0.25499474646585274,
        0.0,
        0.0,
        0.0,
        0.0,
        0.0,
        0.0
      ],
      "triggerTime_ms": 1716,
      "faceAngle": 0.0,
      "leftEye": [
        9.169666010979592,
        0.0,
        1.2882419568399386,
        0.9052803931751328,
        0.0,
        0.31501004380265013,
        0.31501004380265013,
        0.31501004380265013,
        0.31501004380265013,
        0.5,
        0.5,
        0.5,
        0.5,
        0.0,
        0.0,
        0.0,
        0.0,
        0.0,
        0.0
      ]
    },
    {
      "durationTime_ms": 0,
      "faceCenterY": 0.0,
      "faceCenterX": 0.0,
      "Name": "ProceduralFaceKeyFrame",
      "faceScaleY": 1.6275416612625122,
      "faceScaleX": 0.8442620626719509,
      "rightEye": [
        -10.206374107265454,
        0.0,
        1.578522208770766,
        0.9052803931751328,
        0.0,
        0.01,
        0.01,
        0.01,
        0.01,
        0.01,
        0.01,
        0.01,
        0.01,
        0.0,
        0.0,
        0.0,
        0.0,
        0.0,
        0.0
      ],
      "triggerTime_ms": 1749,
      "faceAngle": 0.0,
      "leftEye": [
        9.169666010979592,
        0.0,
        1.2882419568399386,
        0.9052803931751328,
        0.0,
        0.2953651062418813,
        0.2953651062418813,
        0.2953651062418813,
        0.2953651062418813,
        0.5,
        0.5,
        0.5,
        0.5,
        0.0,
        0.0,
        0.0,
        0.0,
        0.0,
        0.0
      ]
    },
    {
      "durationTime_ms": 0,
      "faceCenterY": 15.518261790630278,
      "faceCenterX": 0.0,
      "Name": "ProceduralFaceKeyFrame",
      "faceScaleY": 0.8448529831212924,
      "faceScaleX": 1.0681257247924805,
      "rightEye": [
        -10.206374107265454,
        0.0,
        1.578522208770766,
        0.9052803931751328,
        0.0,
        0.01,
        0.01,
        0.01,
        0.01,
        0.01,
        0.01,
        0.01,
        0.01,
        0.0,
        0.0,
        0.0,
        0.0,
        0.0,
        0.0
      ],
      "triggerTime_ms": 1782,
      "faceAngle": 0.0,
      "leftEye": [
        9.169666010979592,
        0.0,
        1.3655941014490638,
        0.9052803931751328,
        0.0,
        0.11464458578679071,
        0.11464458578679071,
        0.11464458578679071,
        0.11464458578679071,
        0.25499474646585274,
        0.25499474646585274,
        0.25499474646585274,
        0.25499474646585274,
        0.0,
        0.0,
        0.0,
        0.0,
        0.0,
        0.0
      ]
    },
    {
      "durationTime_ms": 0,
      "faceCenterY": 31.035859081214316,
      "faceCenterX": 0.0,
      "Name": "ProceduralFaceKeyFrame",
      "faceScaleY": 0.0746653012631696,
      "faceScaleX": 1.818399429321289,
      "rightEye": [
        -10.206374107265454,
        0.0,
        1.2294163333612094,
        0.9052803931751328,
        0.0,
        0.5,
        0.5,
        0.5,
        0.5,
        0.5,
        0.5,
        0.5,
        0.5,
        0.0,
        0.0,
        0.0,
        0.0,
        0.0,
        0.0
      ],
      "triggerTime_ms": 1815,
      "faceAngle": 0.0,
      "leftEye": [
        9.169666010979592,
        0.0,
        1.5584491201178454,
        0.9052803931751328,
        0.0,
        0.01,
        0.01,
        0.01,
        0.01,
        0.01,
        0.01,
        0.01,
        0.01,
        0.0,
        0.0,
        0.0,
        0.0,
        0.0,
        0.0
      ]
    },
    {
      "durationTime_ms": 0,
      "faceCenterY": 26.94940072039913,
      "faceCenterX": 0.0,
      "Name": "ProceduralFaceKeyFrame",
      "faceScaleY": 0.0746653012631696,
      "faceScaleX": 1.1074296236038208,
      "rightEye": [
        -12.25209194877642,
        0.7977380718408825,
        1.2339788255409456,
        0.8357892005834344,
        0.0,
        0.3070330133758854,
        0.3070330133758854,
        0.3070330133758854,
        0.3070330133758854,
        0.4887487982651066,
        0.4887487982651066,
        0.4887487982651066,
        0.4887487982651066,
        0.0,
        0.0,
        0.0,
        0.0,
        0.0,
        0.0
      ],
      "triggerTime_ms": 1848,
      "faceAngle": 0.0,
      "leftEye": [
        9.169666010979592,
        0.0,
        1.5584491201178454,
        0.9052803931751328,
        0.0,
        0.01,
        0.01,
        0.01,
        0.01,
        0.01,
        0.01,
        0.01,
        0.01,
        0.0,
        0.0,
        0.0,
        0.0,
        0.0,
        0.0
      ]
    },
    {
      "durationTime_ms": 0,
      "faceCenterY": 8.001095406987703,
      "faceCenterX": 0.0,
      "Name": "ProceduralFaceKeyFrame",
      "faceScaleY": 0.94638365464776,
      "faceScaleX": 1.0185850858688354,
      "rightEye": [
        -10.206374107265454,
        0.0,
        1.222310304629302,
        0.9052803931751328,
        0.0,
        0.5,
        0.5,
        0.5,
        0.5,
        0.5,
        0.5,
        0.5,
        0.5,
        0.0,
        0.0,
        0.0,
        0.0,
        0.0,
        0.0
      ],
      "triggerTime_ms": 1881,
      "faceAngle": 0.0,
      "leftEye": [
        9.169666010979592,
        0.0,
        1.2214562337843777,
        0.9052803931751328,
        0.0,
        0.5,
        0.5,
        0.5,
        0.5,
        0.5,
        0.5,
        0.5,
        0.5,
        0.0,
        0.0,
        0.0,
        0.0,
        0.0,
        0.0
      ]
    },
    {
      "durationTime_ms": 0,
      "faceCenterY": 0.0,
      "faceCenterX": 0.0,
      "Name": "ProceduralFaceKeyFrame",
      "faceScaleY": 1.5037992000579834,
      "faceScaleX": 0.8442620626719509,
      "rightEye": [
        -10.206374107265454,
        0.0,
        1.381307639854893,
        0.9052803931751328,
        0.0,
        0.37437365788143206,
        0.37437365788143206,
        0.37437365788143206,
        0.37437365788143206,
        0.37437365788143206,
        0.37437365788143206,
        0.37437365788143206,
        0.37437365788143206,
        0.0,
        0.0,
        0.0,
        0.0,
        0.0,
        0.0
      ],
      "triggerTime_ms": 1914,
      "faceAngle": 0.0,
      "leftEye": [
        9.169666010979592,
        0.0,
        1.2882419568399386,
        0.9052803931751328,
        0.0,
        0.3547092198782442,
        0.3547092198782442,
        0.3547092198782442,
        0.3547092198782442,
        0.5,
        0.5,
        0.5,
        0.5,
        0.0,
        0.0,
        0.0,
        0.0,
        0.0,
        0.0
      ]
    },
    {
      "durationTime_ms": 0,
      "faceCenterY": -11.66014734671063,
      "faceCenterX": 0.0,
      "Name": "ProceduralFaceKeyFrame",
      "faceScaleY": 1.09217369556427,
      "faceScaleX": 0.9706363675462907,
      "rightEye": [
        -10.206374107265454,
        0.0,
        1.381307639854893,
        0.9052803931751328,
        0.0,
        0.37437365788143206,
        0.37437365788143206,
        0.37437365788143206,
        0.37437365788143206,
        0.37437365788143206,
        0.37437365788143206,
        0.37437365788143206,
        0.37437365788143206,
        0.0,
        0.0,
        0.0,
        0.0,
        0.0,
        0.0
      ],
      "triggerTime_ms": 1947,
      "faceAngle": 0.0,
      "leftEye": [
        9.169666010979592,
        0.0,
        1.2145967642052955,
        0.9052803931751328,
        0.0,
        0.5,
        0.5,
        0.5,
        0.5,
        0.5,
        0.5,
        0.5,
        0.5,
        0.0,
        0.0,
        0.0,
        0.0,
        0.0,
        0.0
      ]
    },
    {
      "durationTime_ms": 0,
      "faceCenterY": -15.602840394533183,
      "faceCenterX": 0.0,
      "Name": "ProceduralFaceKeyFrame",
      "faceScaleY": 0.9001836174009837,
      "faceScaleX": 0.9645689722900462,
      "rightEye": [
        -10.206374107265454,
        0.0,
        1.381307639854893,
        0.9052803931751328,
        0.0,
        0.37437365788143206,
        0.37437365788143206,
        0.37437365788143206,
        0.37437365788143206,
        0.37437365788143206,
        0.37437365788143206,
        0.37437365788143206,
        0.37437365788143206,
        0.0,
        0.0,
        0.0,
        0.0,
        0.0,
        0.0
      ],
      "triggerTime_ms": 1980,
      "faceAngle": 0.0,
      "leftEye": [
        9.169666010979592,
        0.0,
        1.3680773403841795,
        0.9052803931751328,
        0.0,
        0.37437365788143206,
        0.37437365788143206,
        0.37437365788143206,
        0.37437365788143206,
        0.37437365788143206,
        0.37437365788143206,
        0.37437365788143206,
        0.37437365788143206,
        0.0,
        0.0,
        0.0,
        0.0,
        0.0,
        0.0
      ]
    },
    {
      "durationTime_ms": 0,
      "faceCenterY": -0.6501183640736119,
      "faceCenterX": 0.0,
      "Name": "ProceduralFaceKeyFrame",
      "faceScaleY": 1.1786426305770874,
      "faceScaleX": 0.9224910730454652,
      "rightEye": [
        -10.206374107265454,
        0.0,
        1.4264887583128198,
        0.9052803931751328,
        0.0,
        0.19628237353939565,
        0.19628237353939565,
        0.19628237353939565,
        0.19628237353939565,
        0.19628237353939565,
        0.19628237353939565,
        0.19628237353939565,
        0.19628237353939565,
        0.0,
        0.0,
        0.0,
        0.0,
        0.0,
        0.0
      ],
      "triggerTime_ms": 2013,
      "faceAngle": 0.0,
      "leftEye": [
        9.169666010979592,
        0.0,
        1.3680773403841795,
        0.9052803931751328,
        0.0,
        0.37437365788143206,
        0.37437365788143206,
        0.37437365788143206,
        0.37437365788143206,
        0.37437365788143206,
        0.37437365788143206,
        0.37437365788143206,
        0.37437365788143206,
        0.0,
        0.0,
        0.0,
        0.0,
        0.0,
        0.0
      ]
    },
    {
      "durationTime_ms": 0,
      "faceCenterY": 14.302602889919173,
      "faceCenterX": 0.0,
      "Name": "ProceduralFaceKeyFrame",
      "faceScaleY": 0.8131685844336158,
      "faceScaleX": 1.05900239944458,
      "rightEye": [
        -10.206374107265454,
        0.0,
        1.224513200148218,
        0.9052803931751328,
        0.0,
        0.5,
        0.5,
        0.5,
        0.5,
        0.5,
        0.5,
        0.5,
        0.5,
        0.0,
        0.0,
        0.0,
        0.0,
        0.0,
        0.0
      ],
      "triggerTime_ms": 2046,
      "faceAngle": 0.0,
      "leftEye": [
        9.169666010979592,
        0.0,
        1.3680773403841795,
        0.9052803931751328,
        0.0,
        0.37437365788143206,
        0.37437365788143206,
        0.37437365788143206,
        0.37437365788143206,
        0.37437365788143206,
        0.37437365788143206,
        0.37437365788143206,
        0.37437365788143206,
        0.0,
        0.0,
        0.0,
        0.0,
        0.0,
        0.0
      ]
    },
    {
      "durationTime_ms": 0,
      "faceCenterY": 16.71732878419505,
      "faceCenterX": 0.0,
      "Name": "ProceduralFaceKeyFrame",
      "faceScaleY": 0.7029415361695098,
      "faceScaleX": 1.05900239944458,
      "rightEye": [
        -10.206374107265454,
        0.0,
        1.381307639854893,
        0.9052803931751328,
        0.0,
        0.37437365788143206,
        0.37437365788143206,
        0.37437365788143206,
        0.37437365788143206,
        0.37437365788143206,
        0.37437365788143206,
        0.37437365788143206,
        0.37437365788143206,
        0.0,
        0.0,
        0.0,
        0.0,
        0.0,
        0.0
      ],
      "triggerTime_ms": 2112,
      "faceAngle": 0.0,
      "leftEye": [
        9.169666010979592,
        0.0,
        1.411690801479561,
        0.9052803931751328,
        0.0,
        0.19628237353939565,
        0.19628237353939565,
        0.19628237353939565,
        0.19628237353939565,
        0.19628237353939565,
        0.19628237353939565,
        0.19628237353939565,
        0.19628237353939565,
        0.0,
        0.0,
        0.0,
        0.0,
        0.0,
        0.0
      ]
    },
    {
      "durationTime_ms": 0,
      "faceCenterY": -13.040090188035327,
      "faceCenterX": 0.0,
      "Name": "ProceduralFaceKeyFrame",
      "faceScaleY": 1.024977207183838,
      "faceScaleX": 0.968512773245912,
      "rightEye": [
        -10.206374107265454,
        0.0,
        1.381307639854893,
        0.9052803931751328,
        0.0,
        0.37437365788143206,
        0.37437365788143206,
        0.37437365788143206,
        0.37437365788143206,
        0.37437365788143206,
        0.37437365788143206,
        0.37437365788143206,
        0.37437365788143206,
        0.0,
        0.0,
        0.0,
        0.0,
        0.0,
        0.0
      ],
      "triggerTime_ms": 2145,
      "faceAngle": 0.0,
      "leftEye": [
        9.169666010979592,
        0.0,
        1.268314995861583,
        0.9052803931751328,
        0.0,
        0.45603077697926026,
        0.45603077697926026,
        0.45603077697926026,
        0.45603077697926026,
        0.45603077697926026,
        0.45603077697926026,
        0.45603077697926026,
        0.45603077697926026,
        0.0,
        0.0,
        0.0,
        0.0,
        0.0,
        0.0
      ]
    },
    {
      "durationTime_ms": 0,
      "faceCenterY": 2.335501940286591,
      "faceCenterX": 0.0,
      "Name": "ProceduralFaceKeyFrame",
      "faceScaleY": 0.9703721997586024,
      "faceScaleX": 0.870394348326513,
      "rightEye": [
        -10.206374107265454,
        0.0,
        1.381307639854893,
        0.9052803931751328,
        0.0,
        0.37437365788143206,
        0.37437365788143206,
        0.37437365788143206,
        0.37437365788143206,
        0.37437365788143206,
        0.37437365788143206,
        0.37437365788143206,
        0.37437365788143206,
        0.0,
        0.0,
        0.0,
        0.0,
        0.0,
        0.0
      ],
      "triggerTime_ms": 2178,
      "faceAngle": 0.0,
      "leftEye": [
        9.169666010979592,
        0.0,
        1.3680773403841795,
        0.9052803931751328,
        0.0,
        0.37437365788143206,
        0.37437365788143206,
        0.37437365788143206,
        0.37437365788143206,
        0.37437365788143206,
        0.37437365788143206,
        0.37437365788143206,
        0.37437365788143206,
        0.0,
        0.0,
        0.0,
        0.0,
        0.0,
        0.0
      ]
    },
    {
      "durationTime_ms": 0,
      "faceCenterY": 2.595119465455156,
      "faceCenterX": 0.0,
      "Name": "ProceduralFaceKeyFrame",
      "faceScaleY": 0.933230638000196,
      "faceScaleX": 0.8988283865871206,
      "rightEye": [
        -10.206374107265454,
        0.0,
        1.381307639854893,
        0.9052803931751328,
        0.0,
        0.37437365788143206,
        0.37437365788143206,
        0.37437365788143206,
        0.37437365788143206,
        0.37437365788143206,
        0.37437365788143206,
        0.37437365788143206,
        0.37437365788143206,
        0.0,
        0.0,
        0.0,
        0.0,
        0.0,
        0.0
      ],
      "triggerTime_ms": 2211,
      "faceAngle": 0.0,
      "leftEye": [
        9.169666010979592,
        0.0,
        1.3680773403841795,
        0.9052803931751328,
        0.0,
        0.37437365788143206,
        0.37437365788143206,
        0.37437365788143206,
        0.37437365788143206,
        0.37437365788143206,
        0.37437365788143206,
        0.37437365788143206,
        0.37437365788143206,
        0.0,
        0.0,
        0.0,
        0.0,
        0.0,
        0.0
      ]
    },
    {
      "durationTime_ms": 0,
      "faceCenterY": 5.943939184288639,
      "faceCenterX": 0.0,
      "Name": "ProceduralFaceKeyFrame",
      "faceScaleY": 0.6351774925941255,
      "faceScaleX": 1.05900239944458,
      "rightEye": [
        -10.206374107265454,
        0.0,
        1.578522208770766,
        0.9052803931751328,
        0.0,
        0.01,
        0.01,
        0.01,
        0.01,
        0.01,
        0.01,
        0.01,
        0.01,
        0.0,
        0.0,
        0.0,
        0.0,
        0.0,
        0.0
      ],
      "triggerTime_ms": 2244,
      "faceAngle": 0.0,
      "leftEye": [
        9.169666010979592,
        0.0,
        1.3680773403841795,
        0.9052803931751328,
        0.0,
        0.03567167623814941,
        0.03567167623814941,
        0.03567167623814941,
        0.03567167623814941,
        0.03567167623814941,
        0.03567167623814941,
        0.03567167623814941,
        0.03567167623814941,
        0.0,
        0.0,
        0.0,
        0.0,
        0.0,
        0.0
      ]
    },
    {
      "durationTime_ms": 0,
      "faceCenterY": 14.501933682715846,
      "faceCenterX": 0.0,
      "Name": "ProceduralFaceKeyFrame",
      "faceScaleY": 0.0746653012631696,
      "faceScaleX": 1.2387584447860718,
      "rightEye": [
        -10.206374107265454,
        0.0,
        1.36807429903117,
        0.9052803931751328,
        0.0,
        0.2992673006823143,
        0.2992673006823143,
        0.2992673006823143,
        0.2992673006823143,
        0.2992673006823143,
        0.2992673006823143,
        0.2992673006823143,
        0.2992673006823143,
        0.0,
        0.0,
        0.0,
        0.0,
        0.0,
        0.0
      ],
      "triggerTime_ms": 2277,
      "faceAngle": 0.0,
      "leftEye": [
        9.169666010979592,
        0.0,
        1.5584491201178454,
        0.9052803931751328,
        0.0,
        0.01,
        0.01,
        0.01,
        0.01,
        0.01,
        0.01,
        0.01,
        0.01,
        0.0,
        0.0,
        0.0,
        0.0,
        0.0,
        0.0
      ]
    },
    {
      "durationTime_ms": 0,
      "faceCenterY": 20.076721124373766,
      "faceCenterX": 0.0,
      "Name": "ProceduralFaceKeyFrame",
      "faceScaleY": 0.0746653012631696,
      "faceScaleX": 1.818399429321289,
      "rightEye": [
        -10.206374107265454,
        0.0,
        1.3892142377371992,
        0.9052803931751328,
        0.0,
        0.3432076704730164,
        0.3432076704730164,
        0.3432076704730164,
        0.3432076704730164,
        0.3432076704730164,
        0.3432076704730164,
        0.3432076704730164,
        0.3432076704730164,
        0.0,
        0.0,
        0.0,
        0.0,
        0.0,
        0.0
      ],
      "triggerTime_ms": 2310,
      "faceAngle": 0.0,
      "leftEye": [
        9.169666010979592,
        0.0,
        1.5584491201178454,
        0.9052803931751328,
        0.0,
        0.01,
        0.01,
        0.01,
        0.01,
        0.01,
        0.01,
        0.01,
        0.01,
        0.0,
        0.0,
        0.0,
        0.0,
        0.0,
        0.0
      ]
    },
    {
      "durationTime_ms": 0,
      "faceCenterY": 15.380037543408209,
      "faceCenterX": 0.0,
      "Name": "ProceduralFaceKeyFrame",
      "faceScaleY": 0.4204335814016775,
      "faceScaleX": 1.176682472229004,
      "rightEye": [
        -10.206374107265454,
        0.0,
        1.2220369777691873,
        0.9052803931751328,
        0.0,
        0.2812541679074967,
        0.2812541679074967,
        0.2812541679074967,
        0.2812541679074967,
        0.2812541679074967,
        0.2812541679074967,
        0.2812541679074967,
        0.2812541679074967,
        0.0,
        0.0,
        0.0,
        0.0,
        0.0,
        0.0
      ],
      "triggerTime_ms": 2343,
      "faceAngle": 0.0,
      "leftEye": [
        9.169666010979592,
        0.0,
        1.244030542236297,
        0.9052803931751328,
        0.0,
        0.2992673006823143,
        0.2992673006823143,
        0.2992673006823143,
        0.2992673006823143,
        0.2992673006823143,
        0.2992673006823143,
        0.2992673006823143,
        0.2992673006823143,
        0.0,
        0.0,
        0.0,
        0.0,
        0.0,
        0.0
      ]
    },
    {
      "durationTime_ms": 0,
      "faceCenterY": 5.328335495272257,
      "faceCenterX": 0.0,
      "Name": "ProceduralFaceKeyFrame",
      "faceScaleY": 1.0977808237075806,
      "faceScaleX": 0.914568960063775,
      "rightEye": [
        -10.206374107265454,
        0.0,
        1.2220369777691873,
        0.9052803931751328,
        0.0,
        0.31543409532479266,
        0.31543409532479266,
        0.31543409532479266,
        0.31543409532479266,
        0.31543409532479266,
        0.31543409532479266,
        0.31543409532479266,
        0.31543409532479266,
        0.0,
        0.0,
        0.0,
        0.0,
        0.0,
        0.0
      ],
      "triggerTime_ms": 2409,
      "faceAngle": 0.0,
      "leftEye": [
        9.169666010979592,
        0.0,
        1.214332921016245,
        0.9052803931751328,
        0.0,
        0.5,
        0.5,
        0.5,
        0.5,
        0.5,
        0.5,
        0.5,
        0.5,
        0.0,
        0.0,
        0.0,
        0.0,
        0.0,
        0.0
      ]
    },
    {
      "durationTime_ms": 0,
      "faceCenterY": 0.0,
      "faceCenterX": 0.0,
      "Name": "ProceduralFaceKeyFrame",
      "faceScaleY": 1.0,
      "faceScaleX": 1.0,
      "rightEye": [
        -10.206374107265454,
        0.0,
        1.2220369777691873,
        0.9052803931751328,
        0.0,
        0.5,
        0.5,
        0.5,
        0.5,
        0.5,
        0.5,
        0.5,
        0.5,
        0.0,
        0.0,
        0.0,
        0.0,
        0.0,
        0.0
      ],
      "triggerTime_ms": 2508,
      "faceAngle": 0.0,
      "leftEye": [
        9.169666010979592,
        0.0,
        1.214332921016245,
        0.9052803931751328,
        0.0,
        0.5,
        0.5,
        0.5,
        0.5,
        0.5,
        0.5,
        0.5,
        0.5,
        0.0,
        0.0,
        0.0,
        0.0,
        0.0,
        0.0
      ]
    },
    {
      "durationTime_ms": 0,
      "faceCenterY": 0.2545371545929243,
      "faceCenterX": 0.0,
      "Name": "ProceduralFaceKeyFrame",
      "faceScaleY": 1.0144295692443848,
      "faceScaleX": 0.9873928426556238,
      "rightEye": [
        -10.206374107265454,
        0.0,
        1.2220369777691873,
        0.9052803931751328,
        0.0,
        0.5,
        0.5,
        0.5,
        0.5,
        0.5,
        0.5,
        0.5,
        0.5,
        0.0,
        0.0,
        0.0,
        0.0,
        0.0,
        0.0
      ],
      "triggerTime_ms": 2805,
      "faceAngle": 0.0,
      "leftEye": [
        9.169666010979592,
        0.0,
        1.214332921016245,
        0.9052803931751328,
        0.0,
        0.5,
        0.5,
        0.5,
        0.5,
        0.5,
        0.5,
        0.5,
        0.5,
        0.0,
        0.0,
        0.0,
        0.0,
        0.0,
        0.0
      ]
    },
    {
      "volume": 1.0,
      "audioName": [
        "Play__Robot_Sfx__Scrn_Curious"
      ],
      "Name": "RobotAudioKeyFrame",
      "probability": 1.0,
      "hasAlts": true,
      "triggerTime_ms": 132.0,
      "audioEventId": [
        1701725212
      ]
    },
    {
      "volume": 1.0,
      "audioName": [
        "Play__Robot_Vo__Shared_Surprised"
      ],
      "Name": "RobotAudioKeyFrame",
      "probability": 1.0,
      "hasAlts": true,
      "triggerTime_ms": 231.0,
      "audioEventId": [
        2054953516
      ]
    },
    {
      "volume": 1.0,
      "audioName": [
        "Play__Robot_Vo__Shared_Effort_Pounce"
      ],
      "Name": "RobotAudioKeyFrame",
      "probability": 1.0,
      "hasAlts": true,
      "triggerTime_ms": 825.0,
      "audioEventId": [
        3727241044
      ]
    },
    {
      "volume": 1.0,
      "audioName": [
        "Play__Robot_Sfx__Srv_Surprised"
      ],
      "Name": "RobotAudioKeyFrame",
      "probability": 1.0,
      "hasAlts": true,
      "triggerTime_ms": 1419.0,
      "audioEventId": [
        1907152766
      ]
    },
    {
      "volume": 1.0,
      "audioName": [
        "Play__Robot_Sfx__Scrn_Happy"
      ],
      "Name": "RobotAudioKeyFrame",
      "probability": 1.0,
      "hasAlts": true,
      "triggerTime_ms": 1815.0,
      "audioEventId": [
        302804072
      ]
    },
    {
      "volume": 1.0,
      "audioName": [
        "Play__Robot_Sfx__Scrn_Blink"
      ],
      "Name": "RobotAudioKeyFrame",
      "probability": 1.0,
      "hasAlts": true,
      "triggerTime_ms": 2310.0,
      "audioEventId": [
        2666670780
      ]
    },
    {
      "volume": 1.0,
      "audioName": [
        "Play__Robot_Sfx__Srv_Surprised_Short"
      ],
      "Name": "RobotAudioKeyFrame",
      "probability": 1.0,
      "hasAlts": true,
      "triggerTime_ms": 2739.0,
      "audioEventId": [
        4054065165
      ]
    },
    {
      "Right": [
        0.0,
        0.0,
        0.0,
        0.0
      ],
      "Name": "BackpackLightsKeyFrame",
      "durationTime_ms": 2805.0,
      "Back": [
        0.0,
        0.0,
        0.0,
        0.0
      ],
      "Middle": [
        0.0,
        0.0,
        0.0,
        0.0
      ],
      "Front": [
        0.0,
        0.0,
        0.0,
        0.0
      ],
      "triggerTime_ms": 0.0,
      "Left": [
        0.0,
        0.0,
        0.0,
        0.0
      ]
    },
    {
      "Right": [
        0.0,
        0.0,
        0.0,
        0.0
      ],
      "Name": "BackpackLightsKeyFrame",
      "durationTime_ms": 495.0,
      "Back": [
        0.0,
        0.0,
        0.0,
        0.0
      ],
      "Middle": [
        0.0,
        0.0,
        0.0,
        0.0
      ],
      "Front": [
        0.0,
        0.0,
        0.0,
        0.0
      ],
      "triggerTime_ms": 2805.0,
      "Left": [
        0.0,
        0.0,
        0.0,
        0.0
      ]
    },
    {
      "durationTime_ms": 165.0,
      "speed": -12.0,
      "triggerTime_ms": 627.0,
      "Name": "BodyMotionKeyFrame",
      "radius_mm": "TURN_IN_PLACE"
    },
    {
      "durationTime_ms": 198.0,
      "speed": -10.0,
      "triggerTime_ms": 792.0,
      "Name": "BodyMotionKeyFrame",
      "radius_mm": "TURN_IN_PLACE"
    },
    {
      "durationTime_ms": 165.0,
      "speed": 61.0,
      "triggerTime_ms": 990.0,
      "Name": "BodyMotionKeyFrame",
      "radius_mm": "TURN_IN_PLACE"
    },
    {
      "durationTime_ms": 198.0,
      "speed": -30.0,
      "triggerTime_ms": 1155.0,
      "Name": "BodyMotionKeyFrame",
      "radius_mm": "TURN_IN_PLACE"
    },
    {
      "durationTime_ms": 99.0,
      "speed": 67.0,
      "triggerTime_ms": 1518.0,
      "Name": "BodyMotionKeyFrame",
      "radius_mm": "STRAIGHT"
    },
    {
      "durationTime_ms": 198.0,
      "speed": -110.0,
      "triggerTime_ms": 1617.0,
      "Name": "BodyMotionKeyFrame",
      "radius_mm": "STRAIGHT"
    }
  ]
}